sanctuary/__init__.py
sanctuary/backend.py
sanctuary/sacred_mongo.py
sanctuary/keras/__init__.py
sanctuary/keras/callbacks.py
sanctuary/keras/capture.py
sanctuary-0.1.2.dist-info/DESCRIPTION.rst
sanctuary-0.1.2.dist-info/METADATA
sanctuary-0.1.2.dist-info/RECORD
sanctuary-0.1.2.dist-info/WHEEL
sanctuary-0.1.2.dist-info/metadata.json
sanctuary-0.1.2.dist-info/top_level.txt
