Metadata-Version: 2.0
Name: sanctuary
Version: 0.1.2
Summary: Managed machine-learning model training tool based on sacred.
Home-page: https://github.com/bzamecnik/sanctuary
Author: Bohumir Zamecnik
Author-email: bohumir.zamecnik@gmail.com
License: MIT
Platform: UNKNOWN
Classifier: Development Status :: 3 - Alpha
Classifier: Intended Audience :: Developers
Classifier: Intended Audience :: Science/Research
Classifier: License :: OSI Approved :: MIT License
Classifier: Programming Language :: Python :: 3
Classifier: Operating System :: POSIX :: Linux
Classifier: Operating System :: MacOS :: MacOS X
Requires-Dist: keras (>=1.1.1)
Requires-Dist: numpy
Requires-Dist: sacred
